README.md
setup.py
AT_finder.egg-info/PKG-INFO
AT_finder.egg-info/SOURCES.txt
AT_finder.egg-info/dependency_links.txt
AT_finder.egg-info/entry_points.txt
AT_finder.egg-info/requires.txt
AT_finder.egg-info/top_level.txt
atFinder/__init__.py
atFinder/atFinder.py