Metadata-Version: 1.0
Name: AT-finder
Version: 0.0.1
Summary: Python CLI for finding A/T rich regions in genbank files.
Home-page: https://github.com/J-E-J-S/AT-finder
Author: James Sanders
Author-email: james.sanders1711@gmail.com
License: UNKNOWN
Platform: UNKNOWN
